Workbook

Sheet README
A1: Apple Pomace to Ethanol - Techno-Economic Analysis
A2: Mark A. Heien - ChemE 486 Process Design II, University of Washington, Spring 2026
A3: First place, Bowen Award.
A5: WHAT THIS FILE IS
A6: The eight AP_ worksheets in this workbook are my own techno-economic model for the
A7: retrofit of Seattle Gas Works Park into a cellulosic ethanol plant fed by Washington
A8: apple pomace. Formulas are live - this is the working model, not a values dump.
A10: PROVENANCE - PLEASE READ
A11: The model was originally built as an added layer inside the NREL biochemical-ethanol
A12: design workbook (dw1910), authored by David Humbird et al. and distributed with NREL
A13: report NREL/TP-5100-47764, "Process Design and Economics for Biochemical Conversion of
A14: Lignocellulosic Biomass to Ethanol" (2011).
... A30: Mark A. Heien - ChemEMarkHeien@gmail.com - linkedin.com/in/markheien

Sheet AP_INPUTS
A1: Apple Pomace TEA Inputs
A2: Input cells can be replaced with your final team values.
A3: Input | B3: Value | C3: Unit | D3: Used for
A4: Current CEPCI | B4: 797.9 | C4: index | D4: Cost escalation
A5: Base CEPCI | B5: 567 | C5: index | D5: Cost escalation
A6: Discount rate | B6: 0.1 | C6: fraction | D6: CRF and NPV
A7: Plant life | B7: 20 | C7: years | D7: CRF and cash flow
A8: Tax rate | B8: 0.21 | C8: fraction | D8: Cash flow
A9: Depreciation years | B9: 7 | C9: years | D9: Cash flow
A10: Operating start year | B10: 3 | C10: year | D10: Cash flow
A11: Annual ethanol production | B11: =B37 | C11: gal/yr | D11: MSP denominator
A12: Market ethanol price | B12: 2.02 | C12: $/gal | D12: NPV check
A13: Annual coproduct credits | B13: 0 | C13: $/yr | D13: Revenue credit
A14: Construction Year 0 % of TCI | B14: 0.4 | C14: fraction | D14: Capital schedule
A15: Construction Year 1 % of TCI | B15: 0.4 | C15: fraction | D15: Capital schedule
A16: Startup Year % of TCI | B16: 0.2 | C16: fraction | D16: Capital schedule
A17: Working capital % of FCI | B17: 0.1 | C17: fraction | D17: TCI/cash flow
A18: Salvage % of FCI | B18: 0 | C18: fraction | D18: Final year credit
A19: Land cost | B19: 0 | C19: $ | D19: TCI
A20: Plant uptime | B20: 0.85 | C20: fraction | D20: Production adjustment
A22: Capital factor defaults from lecture
A23: OSBL as % of ISBL | B23: 0.25 | C23: fraction | D23: CAPEX
A24: Additional direct costs as % of ISBL | B24: 0.175 | C24: fraction | D24: CAPEX
A25: Indirect costs as % of TDC | B25: 0.6 | C25: fraction | D25: CAPEX
A27: OPEX factor defaults
A28: Maintenance % of FCI | B28: 0.03 | C28: fraction | D28: OPEX
A29: Insurance/taxes % of FCI | B29: 0.007 | C29: fraction | D29: OPEX
A30: Plant overhead % of labor | B30: 0.6 | C30: fraction | D30: OPEX
A32: DESIGN BASIS (Aspen run: FINAL_Apple_Fermentation_process; Report 3 Table 6)
A33: Ethanol product stream | B33: 4715.31 | C33: kg/h | D33: Aspen Table 6 final product
A34: Ethanol mass fraction in product | B34: 0.972 | C34: fraction | D34: from 95.3 mol% EtOH / 2.9% H2O / 1.7% CO2
A35: Ethanol density | B35: 0.789 | C35: kg/L | D35: NIST, 20 C
A36: Operating hours per year | B36: =B20*8760 | C36: h/yr | D36: uptime x 8760
A37: Pure ethanol produced | B37: =B33*B34*B36/B35/3.78541 | C37: gal/yr | D37: derived
A38: Apple pomace feed (as fed to process) | B38: 39994 | C38: kg/h | D38: Aspen Table 6 dried-pomace feed
A39: Apple pomace feed (annual) | B39: =B38*B36/1000 | C39: wet t/yr | D39: derived
A40: As-received pomace (report narrative) | B40: 100000 | C40: kg/h | D40: NARRATIVE value; inconsistent w/ Aspen 39,994 - see recommendations
A41: Solids throughput | B41: =B38*24/1000 | C41: t/day | D41: for reactor scaling
A42: Wastewater estimate | B42: 250000 | C42: m3/yr | D42: engineering estimate, pending Aspen

Sheet AP_CAPEX
A1: Apple Pomace TEA CAPEX
A2: Use this as the report-facing CAPEX table. Replace placeholders with team values.
A3: Process Area | B3: Base Equip Cost ($) | C3: Base Capacity | D3: Required Capacity | E3: Exponent n | F3: Base CEPCI | G3: Current CEPCI | H3: Purchased Cost ($) | I3: Install Factor | J3: Installed Cost ($)
A4: Feed receiving/storage | B4: 500000 | C4: 100000 | D4: =AP_INPUTS!B39 | E4: 0.6 | F4: 567 | G4: 797.9 | H4: =IFERROR(B4*(D4/C4)^E4*(G4/F4),0) | I4: 2 | J4: =H4*I4
A5: Slurry preparation | B5: 350000 | C5: 100000 | D5: =AP_INPUTS!B39 | E5: 0.6 | F5: 567 | G5: 797.9 | H5: =IFERROR(B5*(D5/C5)^E5*(G5/F5),0) | I5: 2.5 | J5: =H5*I5
A6: Pretreatment | B6: 3000000 | C6: 2000 | D6: =AP_INPUTS!B41 | E6: 0.6 | F6: 567 | G6: 797.9 | H6: =IFERROR(B6*(D6/C6)^E6*(G6/F6),0) | I6: 2.5 | J6: =H6*I6
A7: Neutralization & conditioning | B7: 600000 | C7: 1000 | D7: =AP_INPUTS!B41 | E7: 0.6 | F7: 567 | G7: 797.9 | H7: =IFERROR(B7*(D7/C7)^E7*(G7/F7),0) | I7: 2.8 | J7: =H7*I7
A8: Fermentation | B8: 2500000 | C8: 1000 | D8: =AP_INPUTS!B41 | E8: 0.6 | F8: 567 | G8: 797.9 | H8: =IFERROR(B8*(D8/C8)^E8*(G8/F8),0) | I8: 2.8 | J8: =H8*I8
A9: Solids separation | B9: 750000 | C9: 100000 | D9: =AP_INPUTS!B39 | E9: 0.6 | F9: 567 | G9: 797.9 | H9: =IFERROR(B9*(D9/C9)^E9*(G9/F9),0) | I9: 2.2 | J9: =H9*I9
A10: Distillation | B10: 4000000 | C10: 10000000 | D10: =AP_INPUTS!B11 | E10: 0.6 | F10: 567 | G10: 797.9 | H10: =IFERROR(B10*(D10/C10)^E10*(G10/F10),0) | I10: 3 | J10: =H10*I10
A11: Molecular sieve dehydration | B11: 1500000 | C11: 10000000 | D11: =AP_INPUTS!B11 | E11: 0.6 | F11: 567 | G11: 797.9 | H11: =IFERROR(B11*(D11/C11)^E11*(G11/F11),0) | I11: 2.6 | J11: =H11*I11
A12: Product storage/loading | B12: 800000 | C12: 10000000 | D12: =AP_INPUTS!B11 | E12: 0.6 | F12: 567 | G12: 797.9 | H12: =IFERROR(B12*(D12/C12)^E12*(G12/F12),0) | I12: 2 | J12: =H12*I12
A13: Wastewater treatment | B13: 1800000 | C13: 500000 | D13: =AP_INPUTS!B42 | E13: 0.6 | F13: 567 | G13: 797.9 | H13: =IFERROR(B13*(D13/C13)^E13*(G13/F13),0) | I13: 2.2 | J13: =H13*I13
A15: ISBL | J15: =SUM(J4:J13)
A16: OSBL | J16: =J15*AP_INPUTS!B23
A17: Additional direct costs | J17: =J15*AP_INPUTS!B24
A18: Total direct costs (TDC) | J18: =SUM(J15:J17)
A19: Indirect costs | J19: =J18*AP_INPUTS!B25
A20: Fixed capital investment (FCI) | J20: =J18+J19
A21: Working capital | J21: =J20*AP_INPUTS!B17
A22: Land | J22: =AP_INPUTS!B19
A23: Total capital investment (TCI) | J23: =SUM(J20:J22)

Sheet AP_OPEX
A1: Apple Pomace TEA OPEX
A2: Use this as the report-facing annual operating cost table.
A3: Cost Item | B3: Annual Amount or Factor | C3: Unit Cost or Multiplier | D3: Annual Cost ($/yr) | E3: Basis
A4: Apple pomace feedstock | B4: =AP_INPUTS!B39 | C4: 20 | D4: =B4*C4 | E4: wet t/yr x $/wet t
A5: Transportation | B5: =AP_INPUTS!B39 | C5: 25 | D5: =B5*C5 | E5: wet t/yr x $/wet t
A6: Enzymes (NOT USED - dilute-acid route) | B6: 0 | C6: 0 | D6: =B6*C6 | E6: replaced by dilute acid
A7: Acid / base chemicals | B7: 200000 | C7: 1 | D7: =B7*C7 | E7: kg/yr x $/kg
A8: Steam / natural gas | B8: 300000 | C8: 8 | D8: =B8*C8 | E8: GJ/yr x $/GJ
A9: Electricity | B9: 10000000 | C9: 0.07 | D9: =B9*C9 | E9: kWh/yr x $/kWh
A10: Cooling water | B10: 1000000 | C10: 0.3 | D10: =B10*C10 | E10: m3/yr x $/m3
A11: Wastewater treatment | B11: =AP_INPUTS!B42 | C11: 2 | D11: =B11*C11 | E11: m3/yr x $/m3
A12: Solids handling/disposal | B12: 150000 | C12: 10 | D12: =B12*C12 | E12: wet t/yr x $/wet t
A13: Operating labor | B13: 60 | C13: 65000 | D13: =B13*C13 | E13: FTE x $/FTE-yr
A14: Maintenance | B14: =AP_INPUTS!B28 | D14: =AP_CAPEX!J20*B14 | E14: % of FCI
A15: Insurance/taxes | B15: =AP_INPUTS!B29 | D15: =AP_CAPEX!J20*B15 | E15: % of FCI
A16: Plant overhead | B16: =AP_INPUTS!B30 | D16: =D13*B16 | E16: % of labor
A17: Administrative/distribution/R&D | B17: 1 | C17: 1500000 | D17: =B17*C17 | E17: annual estimate
A19: Total annual OPEX | D19: =SUM(D4:D17)

Sheet AP_CASHFLOW
A1: Apple Pomace TEA Cash Flow
A2: Market-price NPV uses the market ethanol price from AP_INPUTS.
A3: Year | B3: TCI Spending | C3: Working Capital | D3: Revenue | E3: Coproduct Credits | F3: OPEX | G3: Depreciation | H3: Taxable Income | I3: Taxes | J3: Net Cash Flow | K3: Discount Factor | L3: Discounted Cash Flow | M3: Cumulative NPV | N3: PV Revenue Factor | O3: PV Non-Revenue CF
A4: 0 | B4: =IF(A4=0,-AP_CAPEX!J23*AP_INPUTS!B14,IF(A4=1,-AP_CAPEX!J23*AP_INPUTS!B15,IF(A4=2,-AP_CAPEX!J23*AP_INPUTS!B16,0))) | C4: =IF(A4=2,-AP_CAPEX!J21,IF(A4=AP_INPUTS!B7,AP_CAPEX!J21,0)) | D4: =IF(A4>=AP_INPUTS!B10,AP_INPUTS!B11*AP_INPUTS!B12,0) | E4: =IF(A4>=AP_INPUTS!B10,AP_INPUTS!B13,0) | F4: =IF(A4>=AP_INPUTS!B10,AP_OPEX!D19,0) | G4: =IF(AND(A4>=AP_INPUTS!B10,A4<AP_INPUTS!B10+AP_INPUTS!B9),AP_CAPEX!J20/AP_INPUTS!B9,0) | H4: =D4+E4-F4-G4 | I4: =MAX(0,H4*AP_INPUTS!B8) | J4: =B4+C4+D4+E4-F4-I4 | K4: =1/(1+AP_INPUTS!B6)^A4 | L4: =J4*K4 | M4: =SUM($L$4:L4) | N4: =IF(A4>=AP_INPUTS!B10,AP_INPUTS!B11*(1-AP_INPUTS!B8)*K4,0) | O4: =(B4+C4+((E4-F4-G4)*(1-AP_INPUTS!B8)+G4))*K4
A5: 1 | B5: =IF(A5=0,-AP_CAPEX!J23*AP_INPUTS!B14,IF(A5=1,-AP_CAPEX!J23*AP_INPUTS!B15,IF(A5=2,-AP_CAPEX!J23*AP_INPUTS!B16,0))) | C5: =IF(A5=2,-AP_CAPEX!J21,IF(A5=AP_INPUTS!B7,AP_CAPEX!J21,0)) | D5: =IF(A5>=AP_INPUTS!B10,AP_INPUTS!B11*AP_INPUTS!B12,0) | E5: =IF(A5>=AP_INPUTS!B10,AP_INPUTS!B13,0) | F5: =IF(A5>=AP_INPUTS!B10,AP_OPEX!D19,0) | G5: =IF(AND(A5>=AP_INPUTS!B10,A5<AP_INPUTS!B10+AP_INPUTS!B9),AP_CAPEX!J20/AP_INPUTS!B9,0) | H5: =D5+E5-F5-G5 | I5: =MAX(0,H5*AP_INPUTS!B8) | J5: =B5+C5+D5+E5-F5-I5 | K5: =1/(1+AP_INPUTS!B6)^A5 | L5: =J5*K5 | M5: =SUM($L$4:L5) | N5: =IF(A5>=AP_INPUTS!B10,AP_INPUTS!B11*(1-AP_INPUTS!B8)*K5,0) | O5: =(B5+C5+((E5-F5-G5)*(1-AP_INPUTS!B8)+G5))*K5
A6: 2 | B6: =IF(A6=0,-AP_CAPEX!J23*AP_INPUTS!B14,IF(A6=1,-AP_CAPEX!J23*AP_INPUTS!B15,IF(A6=2,-AP_CAPEX!J23*AP_INPUTS!B16,0))) | C6: =IF(A6=2,-AP_CAPEX!J21,IF(A6=AP_INPUTS!B7,AP_CAPEX!J21,0)) | D6: =IF(A6>=AP_INPUTS!B10,AP_INPUTS!B11*AP_INPUTS!B12,0) | E6: =IF(A6>=AP_INPUTS!B10,AP_INPUTS!B13,0) | F6: =IF(A6>=AP_INPUTS!B10,AP_OPEX!D19,0) | G6: =IF(AND(A6>=AP_INPUTS!B10,A6<AP_INPUTS!B10+AP_INPUTS!B9),AP_CAPEX!J20/AP_INPUTS!B9,0) | H6: =D6+E6-F6-G6 | I6: =MAX(0,H6*AP_INPUTS!B8) | J6: =B6+C6+D6+E6-F6-I6 | K6: =1/(1+AP_INPUTS!B6)^A6 | L6: =J6*K6 | M6: =SUM($L$4:L6) | N6: =IF(A6>=AP_INPUTS!B10,AP_INPUTS!B11*(1-AP_INPUTS!B8)*K6,0) | O6: =(B6+C6+((E6-F6-G6)*(1-AP_INPUTS!B8)+G6))*K6
A7: 3 | B7: =IF(A7=0,-AP_CAPEX!J23*AP_INPUTS!B14,IF(A7=1,-AP_CAPEX!J23*AP_INPUTS!B15,IF(A7=2,-AP_CAPEX!J23*AP_INPUTS!B16,0))) | C7: =IF(A7=2,-AP_CAPEX!J21,IF(A7=AP_INPUTS!B7,AP_CAPEX!J21,0)) | D7: =IF(A7>=AP_INPUTS!B10,AP_INPUTS!B11*AP_INPUTS!B12,0) | E7: =IF(A7>=AP_INPUTS!B10,AP_INPUTS!B13,0) | F7: =IF(A7>=AP_INPUTS!B10,AP_OPEX!D19,0) | G7: =IF(AND(A7>=AP_INPUTS!B10,A7<AP_INPUTS!B10+AP_INPUTS!B9),AP_CAPEX!J20/AP_INPUTS!B9,0) | H7: =D7+E7-F7-G7 | I7: =MAX(0,H7*AP_INPUTS!B8) | J7: =B7+C7+D7+E7-F7-I7 | K7: =1/(1+AP_INPUTS!B6)^A7 | L7: =J7*K7 | M7: =SUM($L$4:L7) | N7: =IF(A7>=AP_INPUTS!B10,AP_INPUTS!B11*(1-AP_INPUTS!B8)*K7,0) | O7: =(B7+C7+((E7-F7-G7)*(1-AP_INPUTS!B8)+G7))*K7
A8: 4 | B8: =IF(A8=0,-AP_CAPEX!J23*AP_INPUTS!B14,IF(A8=1,-AP_CAPEX!J23*AP_INPUTS!B15,IF(A8=2,-AP_CAPEX!J23*AP_INPUTS!B16,0))) | C8: =IF(A8=2,-AP_CAPEX!J21,IF(A8=AP_INPUTS!B7,AP_CAPEX!J21,0)) | D8: =IF(A8>=AP_INPUTS!B10,AP_INPUTS!B11*AP_INPUTS!B12,0) | E8: =IF(A8>=AP_INPUTS!B10,AP_INPUTS!B13,0) | F8: =IF(A8>=AP_INPUTS!B10,AP_OPEX!D19,0) | G8: =IF(AND(A8>=AP_INPUTS!B10,A8<AP_INPUTS!B10+AP_INPUTS!B9),AP_CAPEX!J20/AP_INPUTS!B9,0) | H8: =D8+E8-F8-G8 | I8: =MAX(0,H8*AP_INPUTS!B8) | J8: =B8+C8+D8+E8-F8-I8 | K8: =1/(1+AP_INPUTS!B6)^A8 | L8: =J8*K8 | M8: =SUM($L$4:L8) | N8: =IF(A8>=AP_INPUTS!B10,AP_INPUTS!B11*(1-AP_INPUTS!B8)*K8,0) | O8: =(B8+C8+((E8-F8-G8)*(1-AP_INPUTS!B8)+G8))*K8
A9: 5 | B9: =IF(A9=0,-AP_CAPEX!J23*AP_INPUTS!B14,IF(A9=1,-AP_CAPEX!J23*AP_INPUTS!B15,IF(A9=2,-AP_CAPEX!J23*AP_INPUTS!B16,0))) | C9: =IF(A9=2,-AP_CAPEX!J21,IF(A9=AP_INPUTS!B7,AP_CAPEX!J21,0)) | D9: =IF(A9>=AP_INPUTS!B10,AP_INPUTS!B11*AP_INPUTS!B12,0) | E9: =IF(A9>=AP_INPUTS!B10,AP_INPUTS!B13,0) | F9: =IF(A9>=AP_INPUTS!B10,AP_OPEX!D19,0) | G9: =IF(AND(A9>=AP_INPUTS!B10,A9<AP_INPUTS!B10+AP_INPUTS!B9),AP_CAPEX!J20/AP_INPUTS!B9,0) | H9: =D9+E9-F9-G9 | I9: =MAX(0,H9*AP_INPUTS!B8) | J9: =B9+C9+D9+E9-F9-I9 | K9: =1/(1+AP_INPUTS!B6)^A9 | L9: =J9*K9 | M9: =SUM($L$4:L9) | N9: =IF(A9>=AP_INPUTS!B10,AP_INPUTS!B11*(1-AP_INPUTS!B8)*K9,0) | O9: =(B9+C9+((E9-F9-G9)*(1-AP_INPUTS!B8)+G9))*K9
A10: 6 | B10: =IF(A10=0,-AP_CAPEX!J23*AP_INPUTS!B14,IF(A10=1,-AP_CAPEX!J23*AP_INPUTS!B15,IF(A10=2,-AP_CAPEX!J23*AP_INPUTS!B16,0))) | C10: =IF(A10=2,-AP_CAPEX!J21,IF(A10=AP_INPUTS!B7,AP_CAPEX!J21,0)) | D10: =IF(A10>=AP_INPUTS!B10,AP_INPUTS!B11*AP_INPUTS!B12,0) | E10: =IF(A10>=AP_INPUTS!B10,AP_INPUTS!B13,0) | F10: =IF(A10>=AP_INPUTS!B10,AP_OPEX!D19,0) | G10: =IF(AND(A10>=AP_INPUTS!B10,A10<AP_INPUTS!B10+AP_INPUTS!B9),AP_CAPEX!J20/AP_INPUTS!B9,0) | H10: =D10+E10-F10-G10 | I10: =MAX(0,H10*AP_INPUTS!B8) | J10: =B10+C10+D10+E10-F10-I10 | K10: =1/(1+AP_INPUTS!B6)^A10 | L10: =J10*K10 | M10: =SUM($L$4:L10) | N10: =IF(A10>=AP_INPUTS!B10,AP_INPUTS!B11*(1-AP_INPUTS!B8)*K10,0) | O10: =(B10+C10+((E10-F10-G10)*(1-AP_INPUTS!B8)+G10))*K10
A11: 7 | B11: =IF(A11=0,-AP_CAPEX!J23*AP_INPUTS!B14,IF(A11=1,-AP_CAPEX!J23*AP_INPUTS!B15,IF(A11=2,-AP_CAPEX!J23*AP_INPUTS!B16,0))) | C11: =IF(A11=2,-AP_CAPEX!J21,IF(A11=AP_INPUTS!B7,AP_CAPEX!J21,0)) | D11: =IF(A11>=AP_INPUTS!B10,AP_INPUTS!B11*AP_INPUTS!B12,0) | E11: =IF(A11>=AP_INPUTS!B10,AP_INPUTS!B13,0) | F11: =IF(A11>=AP_INPUTS!B10,AP_OPEX!D19,0) | G11: =IF(AND(A11>=AP_INPUTS!B10,A11<AP_INPUTS!B10+AP_INPUTS!B9),AP_CAPEX!J20/AP_INPUTS!B9,0) | H11: =D11+E11-F11-G11 | I11: =MAX(0,H11*AP_INPUTS!B8) | J11: =B11+C11+D11+E11-F11-I11 | K11: =1/(1+AP_INPUTS!B6)^A11 | L11: =J11*K11 | M11: =SUM($L$4:L11) | N11: =IF(A11>=AP_INPUTS!B10,AP_INPUTS!B11*(1-AP_INPUTS!B8)*K11,0) | O11: =(B11+C11+((E11-F11-G11)*(1-AP_INPUTS!B8)+G11))*K11
A12: 8 | B12: =IF(A12=0,-AP_CAPEX!J23*AP_INPUTS!B14,IF(A12=1,-AP_CAPEX!J23*AP_INPUTS!B15,IF(A12=2,-AP_CAPEX!J23*AP_INPUTS!B16,0))) | C12: =IF(A12=2,-AP_CAPEX!J21,IF(A12=AP_INPUTS!B7,AP_CAPEX!J21,0)) | D12: =IF(A12>=AP_INPUTS!B10,AP_INPUTS!B11*AP_INPUTS!B12,0) | E12: =IF(A12>=AP_INPUTS!B10,AP_INPUTS!B13,0) | F12: =IF(A12>=AP_INPUTS!B10,AP_OPEX!D19,0) | G12: =IF(AND(A12>=AP_INPUTS!B10,A12<AP_INPUTS!B10+AP_INPUTS!B9),AP_CAPEX!J20/AP_INPUTS!B9,0) | H12: =D12+E12-F12-G12 | I12: =MAX(0,H12*AP_INPUTS!B8) | J12: =B12+C12+D12+E12-F12-I12 | K12: =1/(1+AP_INPUTS!B6)^A12 | L12: =J12*K12 | M12: =SUM($L$4:L12) | N12: =IF(A12>=AP_INPUTS!B10,AP_INPUTS!B11*(1-AP_INPUTS!B8)*K12,0) | O12: =(B12+C12+((E12-F12-G12)*(1-AP_INPUTS!B8)+G12))*K12
A13: 9 | B13: =IF(A13=0,-AP_CAPEX!J23*AP_INPUTS!B14,IF(A13=1,-AP_CAPEX!J23*AP_INPUTS!B15,IF(A13=2,-AP_CAPEX!J23*AP_INPUTS!B16,0))) | C13: =IF(A13=2,-AP_CAPEX!J21,IF(A13=AP_INPUTS!B7,AP_CAPEX!J21,0)) | D13: =IF(A13>=AP_INPUTS!B10,AP_INPUTS!B11*AP_INPUTS!B12,0) | E13: =IF(A13>=AP_INPUTS!B10,AP_INPUTS!B13,0) | F13: =IF(A13>=AP_INPUTS!B10,AP_OPEX!D19,0) | G13: =IF(AND(A13>=AP_INPUTS!B10,A13<AP_INPUTS!B10+AP_INPUTS!B9),AP_CAPEX!J20/AP_INPUTS!B9,0) | H13: =D13+E13-F13-G13 | I13: =MAX(0,H13*AP_INPUTS!B8) | J13: =B13+C13+D13+E13-F13-I13 | K13: =1/(1+AP_INPUTS!B6)^A13 | L13: =J13*K13 | M13: =SUM($L$4:L13) | N13: =IF(A13>=AP_INPUTS!B10,AP_INPUTS!B11*(1-AP_INPUTS!B8)*K13,0) | O13: =(B13+C13+((E13-F13-G13)*(1-AP_INPUTS!B8)+G13))*K13
A14: 10 | B14: =IF(A14=0,-AP_CAPEX!J23*AP_INPUTS!B14,IF(A14=1,-AP_CAPEX!J23*AP_INPUTS!B15,IF(A14=2,-AP_CAPEX!J23*AP_INPUTS!B16,0))) | C14: =IF(A14=2,-AP_CAPEX!J21,IF(A14=AP_INPUTS!B7,AP_CAPEX!J21,0)) | D14: =IF(A14>=AP_INPUTS!B10,AP_INPUTS!B11*AP_INPUTS!B12,0) | E14: =IF(A14>=AP_INPUTS!B10,AP_INPUTS!B13,0) | F14: =IF(A14>=AP_INPUTS!B10,AP_OPEX!D19,0) | G14: =IF(AND(A14>=AP_INPUTS!B10,A14<AP_INPUTS!B10+AP_INPUTS!B9),AP_CAPEX!J20/AP_INPUTS!B9,0) | H14: =D14+E14-F14-G14 | I14: =MAX(0,H14*AP_INPUTS!B8) | J14: =B14+C14+D14+E14-F14-I14 | K14: =1/(1+AP_INPUTS!B6)^A14 | L14: =J14*K14 | M14: =SUM($L$4:L14) | N14: =IF(A14>=AP_INPUTS!B10,AP_INPUTS!B11*(1-AP_INPUTS!B8)*K14,0) | O14: =(B14+C14+((E14-F14-G14)*(1-AP_INPUTS!B8)+G14))*K14
A15: 11 | B15: =IF(A15=0,-AP_CAPEX!J23*AP_INPUTS!B14,IF(A15=1,-AP_CAPEX!J23*AP_INPUTS!B15,IF(A15=2,-AP_CAPEX!J23*AP_INPUTS!B16,0))) | C15: =IF(A15=2,-AP_CAPEX!J21,IF(A15=AP_INPUTS!B7,AP_CAPEX!J21,0)) | D15: =IF(A15>=AP_INPUTS!B10,AP_INPUTS!B11*AP_INPUTS!B12,0) | E15: =IF(A15>=AP_INPUTS!B10,AP_INPUTS!B13,0) | F15: =IF(A15>=AP_INPUTS!B10,AP_OPEX!D19,0) | G15: =IF(AND(A15>=AP_INPUTS!B10,A15<AP_INPUTS!B10+AP_INPUTS!B9),AP_CAPEX!J20/AP_INPUTS!B9,0) | H15: =D15+E15-F15-G15 | I15: =MAX(0,H15*AP_INPUTS!B8) | J15: =B15+C15+D15+E15-F15-I15 | K15: =1/(1+AP_INPUTS!B6)^A15 | L15: =J15*K15 | M15: =SUM($L$4:L15) | N15: =IF(A15>=AP_INPUTS!B10,AP_INPUTS!B11*(1-AP_INPUTS!B8)*K15,0) | O15: =(B15+C15+((E15-F15-G15)*(1-AP_INPUTS!B8)+G15))*K15
A16: 12 | B16: =IF(A16=0,-AP_CAPEX!J23*AP_INPUTS!B14,IF(A16=1,-AP_CAPEX!J23*AP_INPUTS!B15,IF(A16=2,-AP_CAPEX!J23*AP_INPUTS!B16,0))) | C16: =IF(A16=2,-AP_CAPEX!J21,IF(A16=AP_INPUTS!B7,AP_CAPEX!J21,0)) | D16: =IF(A16>=AP_INPUTS!B10,AP_INPUTS!B11*AP_INPUTS!B12,0) | E16: =IF(A16>=AP_INPUTS!B10,AP_INPUTS!B13,0) | F16: =IF(A16>=AP_INPUTS!B10,AP_OPEX!D19,0) | G16: =IF(AND(A16>=AP_INPUTS!B10,A16<AP_INPUTS!B10+AP_INPUTS!B9),AP_CAPEX!J20/AP_INPUTS!B9,0) | H16: =D16+E16-F16-G16 | I16: =MAX(0,H16*AP_INPUTS!B8) | J16: =B16+C16+D16+E16-F16-I16 | K16: =1/(1+AP_INPUTS!B6)^A16 | L16: =J16*K16 | M16: =SUM($L$4:L16) | N16: =IF(A16>=AP_INPUTS!B10,AP_INPUTS!B11*(1-AP_INPUTS!B8)*K16,0) | O16: =(B16+C16+((E16-F16-G16)*(1-AP_INPUTS!B8)+G16))*K16
A17: 13 | B17: =IF(A17=0,-AP_CAPEX!J23*AP_INPUTS!B14,IF(A17=1,-AP_CAPEX!J23*AP_INPUTS!B15,IF(A17=2,-AP_CAPEX!J23*AP_INPUTS!B16,0))) | C17: =IF(A17=2,-AP_CAPEX!J21,IF(A17=AP_INPUTS!B7,AP_CAPEX!J21,0)) | D17: =IF(A17>=AP_INPUTS!B10,AP_INPUTS!B11*AP_INPUTS!B12,0) | E17: =IF(A17>=AP_INPUTS!B10,AP_INPUTS!B13,0) | F17: =IF(A17>=AP_INPUTS!B10,AP_OPEX!D19,0) | G17: =IF(AND(A17>=AP_INPUTS!B10,A17<AP_INPUTS!B10+AP_INPUTS!B9),AP_CAPEX!J20/AP_INPUTS!B9,0) | H17: =D17+E17-F17-G17 | I17: =MAX(0,H17*AP_INPUTS!B8) | J17: =B17+C17+D17+E17-F17-I17 | K17: =1/(1+AP_INPUTS!B6)^A17 | L17: =J17*K17 | M17: =SUM($L$4:L17) | N17: =IF(A17>=AP_INPUTS!B10,AP_INPUTS!B11*(1-AP_INPUTS!B8)*K17,0) | O17: =(B17+C17+((E17-F17-G17)*(1-AP_INPUTS!B8)+G17))*K17
A18: 14 | B18: =IF(A18=0,-AP_CAPEX!J23*AP_INPUTS!B14,IF(A18=1,-AP_CAPEX!J23*AP_INPUTS!B15,IF(A18=2,-AP_CAPEX!J23*AP_INPUTS!B16,0))) | C18: =IF(A18=2,-AP_CAPEX!J21,IF(A18=AP_INPUTS!B7,AP_CAPEX!J21,0)) | D18: =IF(A18>=AP_INPUTS!B10,AP_INPUTS!B11*AP_INPUTS!B12,0) | E18: =IF(A18>=AP_INPUTS!B10,AP_INPUTS!B13,0) | F18: =IF(A18>=AP_INPUTS!B10,AP_OPEX!D19,0) | G18: =IF(AND(A18>=AP_INPUTS!B10,A18<AP_INPUTS!B10+AP_INPUTS!B9),AP_CAPEX!J20/AP_INPUTS!B9,0) | H18: =D18+E18-F18-G18 | I18: =MAX(0,H18*AP_INPUTS!B8) | J18: =B18+C18+D18+E18-F18-I18 | K18: =1/(1+AP_INPUTS!B6)^A18 | L18: =J18*K18 | M18: =SUM($L$4:L18) | N18: =IF(A18>=AP_INPUTS!B10,AP_INPUTS!B11*(1-AP_INPUTS!B8)*K18,0) | O18: =(B18+C18+((E18-F18-G18)*(1-AP_INPUTS!B8)+G18))*K18
A19: 15 | B19: =IF(A19=0,-AP_CAPEX!J23*AP_INPUTS!B14,IF(A19=1,-AP_CAPEX!J23*AP_INPUTS!B15,IF(A19=2,-AP_CAPEX!J23*AP_INPUTS!B16,0))) | C19: =IF(A19=2,-AP_CAPEX!J21,IF(A19=AP_INPUTS!B7,AP_CAPEX!J21,0)) | D19: =IF(A19>=AP_INPUTS!B10,AP_INPUTS!B11*AP_INPUTS!B12,0) | E19: =IF(A19>=AP_INPUTS!B10,AP_INPUTS!B13,0) | F19: =IF(A19>=AP_INPUTS!B10,AP_OPEX!D19,0) | G19: =IF(AND(A19>=AP_INPUTS!B10,A19<AP_INPUTS!B10+AP_INPUTS!B9),AP_CAPEX!J20/AP_INPUTS!B9,0) | H19: =D19+E19-F19-G19 | I19: =MAX(0,H19*AP_INPUTS!B8) | J19: =B19+C19+D19+E19-F19-I19 | K19: =1/(1+AP_INPUTS!B6)^A19 | L19: =J19*K19 | M19: =SUM($L$4:L19) | N19: =IF(A19>=AP_INPUTS!B10,AP_INPUTS!B11*(1-AP_INPUTS!B8)*K19,0) | O19: =(B19+C19+((E19-F19-G19)*(1-AP_INPUTS!B8)+G19))*K19
A20: 16 | B20: =IF(A20=0,-AP_CAPEX!J23*AP_INPUTS!B14,IF(A20=1,-AP_CAPEX!J23*AP_INPUTS!B15,IF(A20=2,-AP_CAPEX!J23*AP_INPUTS!B16,0))) | C20: =IF(A20=2,-AP_CAPEX!J21,IF(A20=AP_INPUTS!B7,AP_CAPEX!J21,0)) | D20: =IF(A20>=AP_INPUTS!B10,AP_INPUTS!B11*AP_INPUTS!B12,0) | E20: =IF(A20>=AP_INPUTS!B10,AP_INPUTS!B13,0) | F20: =IF(A20>=AP_INPUTS!B10,AP_OPEX!D19,0) | G20: =IF(AND(A20>=AP_INPUTS!B10,A20<AP_INPUTS!B10+AP_INPUTS!B9),AP_CAPEX!J20/AP_INPUTS!B9,0) | H20: =D20+E20-F20-G20 | I20: =MAX(0,H20*AP_INPUTS!B8) | J20: =B20+C20+D20+E20-F20-I20 | K20: =1/(1+AP_INPUTS!B6)^A20 | L20: =J20*K20 | M20: =SUM($L$4:L20) | N20: =IF(A20>=AP_INPUTS!B10,AP_INPUTS!B11*(1-AP_INPUTS!B8)*K20,0) | O20: =(B20+C20+((E20-F20-G20)*(1-AP_INPUTS!B8)+G20))*K20
A21: 17 | B21: =IF(A21=0,-AP_CAPEX!J23*AP_INPUTS!B14,IF(A21=1,-AP_CAPEX!J23*AP_INPUTS!B15,IF(A21=2,-AP_CAPEX!J23*AP_INPUTS!B16,0))) | C21: =IF(A21=2,-AP_CAPEX!J21,IF(A21=AP_INPUTS!B7,AP_CAPEX!J21,0)) | D21: =IF(A21>=AP_INPUTS!B10,AP_INPUTS!B11*AP_INPUTS!B12,0) | E21: =IF(A21>=AP_INPUTS!B10,AP_INPUTS!B13,0) | F21: =IF(A21>=AP_INPUTS!B10,AP_OPEX!D19,0) | G21: =IF(AND(A21>=AP_INPUTS!B10,A21<AP_INPUTS!B10+AP_INPUTS!B9),AP_CAPEX!J20/AP_INPUTS!B9,0) | H21: =D21+E21-F21-G21 | I21: =MAX(0,H21*AP_INPUTS!B8) | J21: =B21+C21+D21+E21-F21-I21 | K21: =1/(1+AP_INPUTS!B6)^A21 | L21: =J21*K21 | M21: =SUM($L$4:L21) | N21: =IF(A21>=AP_INPUTS!B10,AP_INPUTS!B11*(1-AP_INPUTS!B8)*K21,0) | O21: =(B21+C21+((E21-F21-G21)*(1-AP_INPUTS!B8)+G21))*K21
A22: 18 | B22: =IF(A22=0,-AP_CAPEX!J23*AP_INPUTS!B14,IF(A22=1,-AP_CAPEX!J23*AP_INPUTS!B15,IF(A22=2,-AP_CAPEX!J23*AP_INPUTS!B16,0))) | C22: =IF(A22=2,-AP_CAPEX!J21,IF(A22=AP_INPUTS!B7,AP_CAPEX!J21,0)) | D22: =IF(A22>=AP_INPUTS!B10,AP_INPUTS!B11*AP_INPUTS!B12,0) | E22: =IF(A22>=AP_INPUTS!B10,AP_INPUTS!B13,0) | F22: =IF(A22>=AP_INPUTS!B10,AP_OPEX!D19,0) | G22: =IF(AND(A22>=AP_INPUTS!B10,A22<AP_INPUTS!B10+AP_INPUTS!B9),AP_CAPEX!J20/AP_INPUTS!B9,0) | H22: =D22+E22-F22-G22 | I22: =MAX(0,H22*AP_INPUTS!B8) | J22: =B22+C22+D22+E22-F22-I22 | K22: =1/(1+AP_INPUTS!B6)^A22 | L22: =J22*K22 | M22: =SUM($L$4:L22) | N22: =IF(A22>=AP_INPUTS!B10,AP_INPUTS!B11*(1-AP_INPUTS!B8)*K22,0) | O22: =(B22+C22+((E22-F22-G22)*(1-AP_INPUTS!B8)+G22))*K22
A23: 19 | B23: =IF(A23=0,-AP_CAPEX!J23*AP_INPUTS!B14,IF(A23=1,-AP_CAPEX!J23*AP_INPUTS!B15,IF(A23=2,-AP_CAPEX!J23*AP_INPUTS!B16,0))) | C23: =IF(A23=2,-AP_CAPEX!J21,IF(A23=AP_INPUTS!B7,AP_CAPEX!J21,0)) | D23: =IF(A23>=AP_INPUTS!B10,AP_INPUTS!B11*AP_INPUTS!B12,0) | E23: =IF(A23>=AP_INPUTS!B10,AP_INPUTS!B13,0) | F23: =IF(A23>=AP_INPUTS!B10,AP_OPEX!D19,0) | G23: =IF(AND(A23>=AP_INPUTS!B10,A23<AP_INPUTS!B10+AP_INPUTS!B9),AP_CAPEX!J20/AP_INPUTS!B9,0) | H23: =D23+E23-F23-G23 | I23: =MAX(0,H23*AP_INPUTS!B8) | J23: =B23+C23+D23+E23-F23-I23 | K23: =1/(1+AP_INPUTS!B6)^A23 | L23: =J23*K23 | M23: =SUM($L$4:L23) | N23: =IF(A23>=AP_INPUTS!B10,AP_INPUTS!B11*(1-AP_INPUTS!B8)*K23,0) | O23: =(B23+C23+((E23-F23-G23)*(1-AP_INPUTS!B8)+G23))*K23
A24: 20 | B24: =IF(A24=0,-AP_CAPEX!J23*AP_INPUTS!B14,IF(A24=1,-AP_CAPEX!J23*AP_INPUTS!B15,IF(A24=2,-AP_CAPEX!J23*AP_INPUTS!B16,0))) | C24: =IF(A24=2,-AP_CAPEX!J21,IF(A24=AP_INPUTS!B7,AP_CAPEX!J21,0)) | D24: =IF(A24>=AP_INPUTS!B10,AP_INPUTS!B11*AP_INPUTS!B12,0) | E24: =IF(A24>=AP_INPUTS!B10,AP_INPUTS!B13,0) | F24: =IF(A24>=AP_INPUTS!B10,AP_OPEX!D19,0) | G24: =IF(AND(A24>=AP_INPUTS!B10,A24<AP_INPUTS!B10+AP_INPUTS!B9),AP_CAPEX!J20/AP_INPUTS!B9,0) | H24: =D24+E24-F24-G24 | I24: =MAX(0,H24*AP_INPUTS!B8) | J24: =B24+C24+D24+E24-F24-I24 | K24: =1/(1+AP_INPUTS!B6)^A24 | L24: =J24*K24 | M24: =SUM($L$4:L24) | N24: =IF(A24>=AP_INPUTS!B10,AP_INPUTS!B11*(1-AP_INPUTS!B8)*K24,0) | O24: =(B24+C24+((E24-F24-G24)*(1-AP_INPUTS!B8)+G24))*K24

Sheet AP_REPORT_OUTPUTS
A1: Apple Pomace TEA Report Outputs
A2: Use these values when writing the economics discussion.
A3: Output | B3: Value | C3: Formula Source
A4: ISBL | B4: =AP_CAPEX!J15 | C4: Sum of installed process equipment
A5: FCI | B5: =AP_CAPEX!J20 | C5: TDC plus indirect costs
A6: TCI | B6: =AP_CAPEX!J23 | C6: FCI plus working capital and land
A7: Annual OPEX | B7: =AP_OPEX!D19 | C7: Annual operating cost table
A8: CRF | B8: =AP_INPUTS!B6*(1+AP_INPUTS!B6)^AP_INPUTS!B7/((1+AP_INPUTS!B6)^AP_INPUTS!B7-1) | C8: Lecture CRF formula
A9: Annualized CAPEX | B9: =B6*B8 | C9: TCI x CRF
A10: CRF-based MSP ($/gal) | B10: =(B9+B7-AP_INPUTS!B13)/AP_INPUTS!B11 | C10: Quick MSP check
A11: NPV at market price | B11: =AP_CASHFLOW!M24 | C11: 20-year discounted cash flow
A12: NPV-based MSP ($/gal) | B12: =MAX(0,-SUM(AP_CASHFLOW!O4:O24)/SUM(AP_CASHFLOW!N4:N24)) | C12: Price needed for NPV = 0
A13: Market price comparison | B13: =AP_INPUTS!B12-B12 | C13: Positive means market price is above NPV-based MSP
A14: Recommendation flag | B14: =IF(B12<=AP_INPUTS!B12,"Economically promising at market price","Needs lower costs, better yield, or credits") | C14: Simple decision indicator
A15: IRR at market price | B15: =IFERROR(IRR(AP_CASHFLOW!J4:J24),"undefined - no positive cash flow") | C15: Internal rate of return on net cash flow at $2.02/gal
A16: Annual ethanol (gal/yr) | B16: =AP_INPUTS!B11 | C16: Design-basis production
A17: Annual revenue at market ($) | B17: =AP_INPUTS!B11*AP_INPUTS!B12 | C17: Production x market price
A18: Annual OPEX per gallon ($/gal) | B18: =AP_OPEX!D19/AP_INPUTS!B11 | C18: Total operating cost intensity
A19: Variable OPEX per gallon ($/gal) | B19: =(AP_OPEX!D4+AP_OPEX!D5+AP_OPEX!D7+AP_OPEX!D8+AP_OPEX!D9+AP_OPEX!D10+AP_OPEX!D11+AP_OPEX!D12)/AP_INPUTS!B11 | C19: Cash variable cost per gallon
A20: Cold check: market price vs MSP | B20: =IF(AP_INPUTS!B12>=B12,"Viable","NOT viable at market price") | C20: Decision

Sheet AP_SENSITIVITY
A1: Apple Pomace TEA Sensitivity Analysis
A2: Tornado-plot table. Each variable swung to a low/high case; MSP recomputed (CRF method). Deltas are vs base MSP (AP_REPORT_OUTPUTS!B10). | J2: Tornado data (MSP $/gal change vs base; sorted by impact)
A3: Variable | B3: Low Case | C3: Base Case | D3: High Case | E3: MSP at Low | F3: MSP at High | G3: Low Delta | H3: High Delta | J3: Variable | K3: Low-case | L3: High-case
A4: Total capital investment | B4: =0.7*AP_CAPEX!J23 | C4: =AP_CAPEX!J23 | D4: =1.5*AP_CAPEX!J23 | E4: =(B4*(AP_INPUTS!B6*(1+AP_INPUTS!B6)^AP_INPUTS!B7/((1+AP_INPUTS!B6)^AP_INPUTS!B7-1))+AP_OPEX!D19-AP_INPUTS!B13)/AP_INPUTS!B11 | F4: =(D4*(AP_INPUTS!B6*(1+AP_INPUTS!B6)^AP_INPUTS!B7/((1+AP_INPUTS!B6)^AP_INPUTS!B7-1))+AP_OPEX!D19-AP_INPUTS!B13)/AP_INPUTS!B11 | G4: =E4-AP_REPORT_OUTPUTS!$B$10 | H4: =F4-AP_REPORT_OUTPUTS!$B$10 | J4: Steam/natural gas | K4: =G12 | L4: =H12
A5: Annual OPEX | B5: =0.8*AP_OPEX!D19 | C5: =AP_OPEX!D19 | D5: =1.2*AP_OPEX!D19 | E5: =(AP_CAPEX!J23*AP_REPORT_OUTPUTS!B8+B5-AP_INPUTS!B13)/AP_INPUTS!B11 | F5: =(AP_CAPEX!J23*AP_REPORT_OUTPUTS!B8+D5-AP_INPUTS!B13)/AP_INPUTS!B11 | G5: =E5-AP_REPORT_OUTPUTS!$B$10 | H5: =F5-AP_REPORT_OUTPUTS!$B$10 | J5: Plant life | K5: =G8 | L5: =H8
A6: Annual ethanol production | B6: =0.85*AP_INPUTS!B11 | C6: =AP_INPUTS!B11 | D6: =1.1*AP_INPUTS!B11 | E6: =(AP_REPORT_OUTPUTS!B9+AP_OPEX!D19-AP_INPUTS!B13)/B6 | F6: =(AP_REPORT_OUTPUTS!B9+AP_OPEX!D19-AP_INPUTS!B13)/D6 | G6: =E6-AP_REPORT_OUTPUTS!$B$10 | H6: =F6-AP_REPORT_OUTPUTS!$B$10 | J6: Discount rate | K6: =G7 | L6: =H7
A7: Discount rate | B7: 0.08 | C7: =AP_INPUTS!B6 | D7: 0.15 | E7: =(AP_CAPEX!J23*(B7*(1+B7)^AP_INPUTS!B7/((1+B7)^AP_INPUTS!B7-1))+AP_OPEX!D19-AP_INPUTS!B13)/AP_INPUTS!B11 | F7: =(AP_CAPEX!J23*(D7*(1+D7)^AP_INPUTS!B7/((1+D7)^AP_INPUTS!B7-1))+AP_OPEX!D19-AP_INPUTS!B13)/AP_INPUTS!B11 | G7: =E7-AP_REPORT_OUTPUTS!$B$10 | H7: =F7-AP_REPORT_OUTPUTS!$B$10 | J7: Apple pomace feedstock | K7: =G10 | L7: =H10
A8: Plant life | B8: 15 | C8: =AP_INPUTS!B7 | D8: 30 | E8: =(AP_CAPEX!J23*(AP_INPUTS!B6*(1+AP_INPUTS!B6)^B8/((1+AP_INPUTS!B6)^B8-1))+AP_OPEX!D19-AP_INPUTS!B13)/AP_INPUTS!B11 | F8: =(AP_CAPEX!J23*(AP_INPUTS!B6*(1+AP_INPUTS!B6)^D8/((1+AP_INPUTS!B6)^D8-1))+AP_OPEX!D19-AP_INPUTS!B13)/AP_INPUTS!B11 | G8: =E8-AP_REPORT_OUTPUTS!$B$10 | H8: =F8-AP_REPORT_OUTPUTS!$B$10 | J8: Feedstock transport | K8: =G11 | L8: =H11
A9: Coproduct/policy credit | B9: 0 | C9: =AP_INPUTS!B13 | D9: =AP_INPUTS!B13+1000000 | E9: =(AP_REPORT_OUTPUTS!B9+AP_OPEX!D19-B9)/AP_INPUTS!B11 | F9: =(AP_REPORT_OUTPUTS!B9+AP_OPEX!D19-D9)/AP_INPUTS!B11 | G9: =E9-AP_REPORT_OUTPUTS!$B$10 | H9: =F9-AP_REPORT_OUTPUTS!$B$10 | J9: Annual OPEX | K9: =G5 | L9: =H5
A10: Apple pomace feedstock cost | B10: =0.5*AP_OPEX!D4 | C10: =AP_OPEX!D4 | D10: =2*AP_OPEX!D4 | E10: =(AP_REPORT_OUTPUTS!B9+(AP_OPEX!D19-AP_OPEX!D4+B10)-AP_INPUTS!B13)/AP_INPUTS!B11 | F10: =(AP_REPORT_OUTPUTS!B9+(AP_OPEX!D19-AP_OPEX!D4+D10)-AP_INPUTS!B13)/AP_INPUTS!B11 | G10: =E10-AP_REPORT_OUTPUTS!$B$10 | H10: =F10-AP_REPORT_OUTPUTS!$B$10 | J10: Annual ethanol production | K10: =G6 | L10: =H6
A11: Feedstock transport cost | B11: =0.5*AP_OPEX!D5 | C11: =AP_OPEX!D5 | D11: =2*AP_OPEX!D5 | E11: =(AP_REPORT_OUTPUTS!B9+(AP_OPEX!D19-AP_OPEX!D5+B11)-AP_INPUTS!B13)/AP_INPUTS!B11 | F11: =(AP_REPORT_OUTPUTS!B9+(AP_OPEX!D19-AP_OPEX!D5+D11)-AP_INPUTS!B13)/AP_INPUTS!B11 | G11: =E11-AP_REPORT_OUTPUTS!$B$10 | H11: =F11-AP_REPORT_OUTPUTS!$B$10 | J11: Total capital investment | K11: =G4 | L11: =H4
A12: Steam/natural gas cost | B12: =0.7*AP_OPEX!D8 | C12: =AP_OPEX!D8 | D12: =1.5*AP_OPEX!D8 | E12: =(AP_REPORT_OUTPUTS!B9+(AP_OPEX!D19-AP_OPEX!D8+B12)-AP_INPUTS!B13)/AP_INPUTS!B11 | F12: =(AP_REPORT_OUTPUTS!B9+(AP_OPEX!D19-AP_OPEX!D8+D12)-AP_INPUTS!B13)/AP_INPUTS!B11 | G12: =E12-AP_REPORT_OUTPUTS!$B$10 | H12: =F12-AP_REPORT_OUTPUTS!$B$10
A13: Electricity cost | B13: =0.7*AP_OPEX!D9 | C13: =AP_OPEX!D9 | D13: =1.5*AP_OPEX!D9 | E13: =(AP_REPORT_OUTPUTS!B9+(AP_OPEX!D19-AP_OPEX!D9+B13)-AP_INPUTS!B13)/AP_INPUTS!B11 | F13: =(AP_REPORT_OUTPUTS!B9+(AP_OPEX!D19-AP_OPEX!D9+D13)-AP_INPUTS!B13)/AP_INPUTS!B11 | G13: =E13-AP_REPORT_OUTPUTS!$B$10 | H13: =F13-AP_REPORT_OUTPUTS!$B$10
A14: Wastewater treatment cost | B14: =0.7*AP_OPEX!D11 | C14: =AP_OPEX!D11 | D14: =1.5*AP_OPEX!D11 | E14: =(AP_REPORT_OUTPUTS!B9+(AP_OPEX!D19-AP_OPEX!D11+B14)-AP_INPUTS!B13)/AP_INPUTS!B11 | F14: =(AP_REPORT_OUTPUTS!B9+(AP_OPEX!D19-AP_OPEX!D11+D14)-AP_INPUTS!B13)/AP_INPUTS!B11 | G14: =E14-AP_REPORT_OUTPUTS!$B$10 | H14: =F14-AP_REPORT_OUTPUTS!$B$10

Sheet AP_FORMULA_MAP
A1: Lecture Formula Map
A2: Formula | B2: Plain-language meaning | C2: Where it is used
A3: Ca = Cb*(Aa/Ab)^n | B3: Scale an equipment cost from one size to another. | C3: AP_CAPEX purchased cost
A4: C2 = C1*(I2/I1) | B4: Update old equipment cost to current cost using CEPCI. | C4: AP_CAPEX purchased cost
A5: Installed cost = equipment cost x installation factor | B5: Turn purchased equipment cost into installed equipment cost. | C5: AP_CAPEX installed cost
A6: ISBL = sum installed equipment | B6: Inside-battery-limits cost is the sum of installed process equipment. | C6: AP_CAPEX ISBL
A7: OSBL = 25% of ISBL | B7: Outside utilities and support systems are estimated as a fraction of ISBL. | C7: AP_CAPEX OSBL
A8: Additional direct = 17.5% of ISBL | B8: Site/building/service costs are estimated as a fraction of ISBL. | C8: AP_CAPEX additional direct
A9: Indirect = 60% of TDC | B9: Fees, taxes, construction overhead, and contractor expenses are factored from direct cost. | C9: AP_CAPEX indirect costs
A10: Cs,u = a*CEPCI + b*Cs,f | B10: Estimate utility price from cost index and fuel price. | C10: AP_OPEX formula map
A11: CRF = r(1+r)^n / ((1+r)^n - 1) | B11: Convert capital cost into equivalent annual cost. | C11: AP_REPORT_OUTPUTS CRF
A12: Annualized CAPEX = TCI*CRF | B12: Spread capital cost over project life. | C12: AP_REPORT_OUTPUTS annualized CAPEX
A13: MSP = (annualized CAPEX + OPEX - credits)/annual production | B13: Quick break-even selling price. | C13: AP_REPORT_OUTPUTS CRF-based MSP
... A16: Sensitivity analysis | B16: Change one input at a time and recalculate MSP. | C16: AP_SENSITIVITY

Sheet AP_COMPARISON
A1: 1900s Coal->City Gas vs. Modern Apple-Pomace->Ethanol Retrofit
A2: Profitability comparison (order-of-magnitude). Coal baseline = Report 2 Lake Station model.
A4: Metric | B4: 1900s Coal -> City Gas | C4: Modern Pomace -> Ethanol | D4: Comment
A5: Primary feedstock | B5: Sub-bituminous coal | C5: Apple pomace (wet by-product) | D5: Renewable vs fossil
A6: Feed rate | B6: 7,100 kg/h (170 t/day) | C6: 39,994 kg/h (960 t/day) | D6: Pomace is mostly water
A7: Main product | B7: 170,000 Nm3/day city gas | C7: =TEXT(AP_INPUTS!B11/1000000,"0.0")&" MM gal/yr ethanol" | D7: Fuel vs lighting gas
A8: Product energy output (GJ/h) | B8: 85 | C8: =AP_INPUTS!B33*AP_INPUTS!B34*21.1/1000*(1/AP_INPUTS!B35) | D8: Ethanol LHV 21.1 MJ/L; ethanol plant exports more energy
A9: Capital basis | B9: Existing 1900s plant (sunk) | C9: =ROUND(AP_CAPEX!J23/1000000,0)&" $MM retrofit TCI" | D9: New process equipment required
A10: Annual operating cost | B10: Coal + labor (regulated) | C10: =ROUND(AP_OPEX!D19/1000000,1)&" $MM/yr" | D10: Feedstock logistics + drying dominate
A11: Unit production cost | B11: Set by utility rate base | C11: =TEXT(AP_REPORT_OUTPUTS!B12,"$0.00")&"/gal (MSP)" | D11: Modern plant is a high-cost producer
A12: Market / selling price | B12: Regulated tariff (assured) | C12: =TEXT(AP_INPUTS!B12,"$0.00")&"/gal (commodity)" | D12: Price-taker vs price-setter
A13: Competition | B13: Local monopoly, no substitute | C13: Corn ethanol ~$1.5-2.2, cellulosic ~$2.15/gal | D13: Global commodity market
A14: Margin / viability | B14: Profitable (cost-of-service return) | C14: =IF(AP_INPUTS!B12>=AP_REPORT_OUTPUTS!B12,"Marginal","Unprofitable: MSP > market price") | D14: Structural difference in business model
A16: KEY TAKEAWAY: The 1900s coal->city-gas works was a REGULATED MUNICIPAL UTILITY producing an essential, non-substitutable, locally distributed product under cost-of-service pricing, so a return was effectively assured. The modern retrofit produces a globally traded COMMODITY fuel as a small, high-cost producer; its minimum selling price (~$4.3-4.9/gal) exceeds the market price ($2.02/gal), so it cannot earn a positive margin at design scale. The retrofit is cleaner and exports more energy, but is LESS profitable because of (1) market structure (price-taker vs regulated) and (2) the cost of hauling and drying a wet, low-density by-product. Viability would require larger scale, near-zero feedstock+transport cost, co-products, or a low-carbon-fuel policy credit.
